pythub/__init__.py
pythub/categorical_encoder.py
pythub/changing_value.py
pythub/data_frame_loader.py
pythub/data_frame_modifier.py
pythub/data_sorter.py
pythub/data_type_converter.py
pythub/date_time_handler.py
pythub/feature_engineer.py
pythub/missing_value_handler.py
pythub/outlier_handler.py
pythub/scaler.py
pythub/setup.py
pythub/text_cleaner.py
pythub-0.1.2.dist-info/METADATA
pythub-0.1.2.dist-info/WHEEL
pythub-0.1.2.dist-info/top_level.txt
pythub-0.1.2.dist-info/RECORD
