Metadata-Version: 2.1
Name: pythub
Version: 0.1.2
Summary: A comprehensive Python library for data preprocessing tasks
Home-page: https://github.com/mehmetrecep/pythub
Author: MOHAMED RAGAB ABDELFATTAH ABDELFADEEL-MHD Alhabeb Alshalah-AHMED EMAD ELSAYED MOHAMED ABDELFATTAH
Author-email: mehmetrecep650@gmail.com
Classifier: Programming Language :: Python :: 3
Classifier: License :: OSI Approved :: MIT License
Classifier: Operating System :: OS Independent
Requires-Python: >=3.6
Requires-Dist: pandas
Requires-Dist: numpy
Requires-Dist: scikit-learn
Requires-Dist: nltk
